[
	{
		"tournament": "Birdsong Challenge",
		"start date": "2014-04-29",
		"end date": "2014-05-05"
	},
	{
		"tournament": "May Day Tour",
		"start date": "2014-05-06",
		"end date": "2014-05-12",
		"days": [
			{
				"name": "First Day Legacy Tour",
				"holes": 9,
				"direction": "in",	
				"date": "2014-05-06",
				"score": 20,
				"points": -140,
				"rank": 823,
				"players": 908,
				"rank percent": 91,
				"tour points": 2
			},
			{
				"name": "Day 2 Northern Fox tour",
				"holes": 9,
				"direction": "in",
				"tee": "Long Tee (Mirror)",
				"rules": ["Gale Force"]
			},
			{
				"name": "Day 3 Maple Leaf tour",
				"holes": 18,
				"tee": "Long Tee (Mirror)",
				"rules": ["No shot within 15 sec: +1"]
			}
		]
	},
	{
		"tournament": "Europe Day Memorial",
		"start date": "2014-05-13",
		"end date": "2014-05-19",
		"days" : [
			{
				"name": "First Day Kagurayama tour",
				"holes": 9,
				"direction": "in",
				"tee": "Regular Tee"
				
			},
			{
				"name": "Day 2 Harvest Hills tour",
				"holes": 18,
				"tee": "Long Tee (Mirror)",
				"rules": ["Bunker: +1"]
			},
			{
				"name": "Day 3 Al Arabian tour",
				"holes": 9,
				"direction": "out",
				"tee": "Long Tee (Mirror)",
				"rules": ["Intermediate Only"]
			},
			{
				"name": "Day 4 La Provence tour",
				"holes": 9,
				"direction": "out",
				"tee": "Regular Tee",
				"rules": ["Teeny Cup"]
			},
			{
				"name": "Day 5 Mar Cielo tour",
				"holes": 18,
				"tee": "Regular Tee",
				"rules": ["Gale Force", "Rainy"]
			},
			{
				"name": "Last Day Maple Leaf tour",
				"holes": 18,
				"tee": "Regular Tee",
				"rules": ["Hole Shuffle"]
			}
		]
	},
	{
		"tournament": "Sunburst Championship",
		"start date": "2014-05-20",
		"end date": "2014-05-26",
		"days": [
			{
				"name": "First Day La Provence tour",
				"holes": 18,
				"tee": "Long Tee (Mirror)",
				"rules": ["Hole Shuffle", "Mega Cup"]
			}
		]
	}
]